LICENSE.txt
MANIFEST.in
README.rst
setup.py
docs/SpiralMatrix.rst
docs/images/spiral_matrix_5+axes+bearing_south+right+file_lorem_ipsum.png
docs/images/spiral_matrix_5+command_line.png
docs/images/spiral_matrix_5.png
docs/images/spiral_matrix_7+axes+bearing_south+center1000+step-300.png
docs/images/spiral_matrix_9+right+words_stormy_night.png
spiral_matrix/__init__.py
spiral_matrix/command_line.py
spiral_matrix/spiral_matrix.py
spiral_matrix.egg-info/PKG-INFO
spiral_matrix.egg-info/SOURCES.txt
spiral_matrix.egg-info/dependency_links.txt
spiral_matrix.egg-info/entry_points.txt
spiral_matrix.egg-info/top_level.txt