Metadata-Version: 1.2
Name: spiral-matrix
Version: 0.1.4
Summary: Generate a square 2-d matrix with an outward-spiraling series of elements
Home-page: https://github.com/zero2cx/spiral-matrix
Author: David Schenck
Author-email: zero2cx@gmail.com
License: GPL3+
Keywords: spiral-matrix,2d-matrix,matrix,command-line,console
Platform: UNKNOWN
Classifier: License :: OSI Approved :: GNU General Public License v3 or later (GPLv3+)
Classifier: Programming Language :: Python :: 3
Classifier: Operating System :: OS Independent
Classifier: Environment :: Console
Classifier: Development Status :: 4 - Beta
Requires-Python: >=3
